hacs_models/__init__.py
hacs_models/actor.py
hacs_models/agent_message.py
hacs_models/allergy_intolerance.py
hacs_models/base_resource.py
hacs_models/condition.py
hacs_models/diagnostic_report.py
hacs_models/encounter.py
hacs_models/evidence.py
hacs_models/goal.py
hacs_models/medication.py
hacs_models/medication_request.py
hacs_models/memory.py
hacs_models/observation.py
hacs_models/organization.py
hacs_models/patient.py
hacs_models/practitioner.py
hacs_models/procedure.py
hacs_models/resource_bundle.py
hacs_models/results.py
hacs_models/service_request.py
hacs_models/types.py
hacs_models/workflow.py
hacs_models-0.4.3.dist-info/METADATA
hacs_models-0.4.3.dist-info/WHEEL
hacs_models-0.4.3.dist-info/RECORD
