Metadata-Version: 2.4
Name: hacs-models
Version: 0.4.3
Summary: HACS Healthcare Data Models - Pure Pydantic models for FHIR-compliant healthcare data
Project-URL: Homepage, https://github.com/solanovisitor/hacs-ai
Project-URL: Documentation, https://github.com/solanovisitor/hacs-ai/blob/main/docs/
Project-URL: Repository, https://github.com/solanovisitor/hacs-ai
Project-URL: Issues, https://github.com/solanovisitor/hacs-ai/issues
Project-URL: Changelog, https://github.com/solanovisitor/hacs-ai/blob/main/CHANGELOG.md
Author-email: Solano Todeschini <solanovisitor@gmail.com>
Maintainer-email: Solano Todeschini <solanovisitor@gmail.com>
License: MIT
Keywords: agents,ai,fhir,healthcare,models,pydantic
Classifier: Development Status :: 4 - Beta
Classifier: Intended Audience :: Developers
Classifier: Intended Audience :: Healthcare Industry
Classifier: License :: OSI Approved :: MIT License
Classifier: Programming Language :: Python :: 3
Classifier: Programming Language :: Python :: 3.11
Classifier: Programming Language :: Python :: 3.12
Classifier: Programming Language :: Python :: 3.13
Classifier: Topic :: Scientific/Engineering :: Medical Science Apps.
Classifier: Topic :: Software Development :: Libraries :: Python Modules
Classifier: Typing :: Typed
Requires-Python: >=3.11
Requires-Dist: pydantic>=2.11.7
Requires-Dist: typing-extensions>=4.12.2
Provides-Extra: dev
Requires-Dist: mypy>=1.13.0; extra == 'dev'
Requires-Dist: pytest-asyncio>=0.21.1; extra == 'dev'
Requires-Dist: pytest-cov>=4.0.0; extra == 'dev'
Requires-Dist: pytest>=8.3.4; extra == 'dev'
Requires-Dist: ruff>=0.8.4; extra == 'dev'
